{
    "wisconsin": {
        "Metric": {
            "RAE": [
                1.1,
                0.09
            ],
            "RRSE": [
                1.14,
                0.08
            ]
        },
        "Leaves": [
            2.17,
            1.21
        ],
        "RunTimes": {
            "0": [
                0.06,
                0.05
            ],
            "1": [
                122.0,
                81.45
            ],
            "2": [
                1818.32,
                1812.53
            ],
            "3": [
                1815.8,
                1809.54
            ]
        }
    },
    "pwLinear": {
        "Metric": {
            "RAE": [
                0.36,
                0.06
            ],
            "RRSE": [
                0.36,
                0.04
            ]
        },
        "Leaves": [
            2.2,
            0.48
        ],
        "RunTimes": {
            "0": [
                0.17,
                0.08
            ],
            "1": [
                4.19,
                3.14
            ],
            "2": [
                1551.24,
                1121.19
            ],
            "3": [
                1818.25,
                1785.14
            ]
        }
    },
    "cpu": {
        "Metric": {
            "RAE": [
                0.13,
                0.05
            ],
            "RRSE": [
                0.21,
                0.1
            ]
        },
        "Leaves": [
            3.1,
            0.83
        ],
        "RunTimes": {
            "0": [
                0.31,
                0.17
            ],
            "1": [
                11.96,
                8.72
            ],
            "2": [
                1810.21,
                1804.72
            ],
            "3": [
                1813.12,
                1808.17
            ]
        }
    },
    "yacht_hydrodynamics": {
        "Metric": {
            "RAE": [
                0.13,
                0.02
            ],
            "RRSE": [
                0.18,
                0.02
            ]
        },
        "Leaves": [
            3.57,
            0.5
        ],
        "RunTimes": {
            "0": [
                0.23,
                0.11
            ],
            "1": [
                8.37,
                6.57
            ],
            "2": [
                1814.98,
                1808.27
            ],
            "3": [
                1816.45,
                1809.67
            ]
        }
    },
    "RAM_price": {
        "Metric": {
            "RAE": [
                1.24,
                1.82
            ],
            "RRSE": [
                2.23,
                3.17
            ]
        },
        "Leaves": [
            2.1,
            1.16
        ],
        "RunTimes": {
            "0": [
                0.24,
                0.13
            ],
            "1": [
                15.03,
                4.54
            ],
            "2": [
                1223.69,
                602.75
            ],
            "3": [
                1484.49,
                517.12
            ]
        }
    },
    "autoMpg": {
        "Metric": {
            "RAE": [
                0.92,
                0.15
            ],
            "RRSE": [
                0.98,
                0.14
            ]
        },
        "Leaves": [
            3.13,
            0.81
        ],
        "RunTimes": {
            "0": [
                0.08,
                0.07
            ],
            "1": [
                51.84,
                43.64
            ],
            "2": [
                1799.9,
                1799.35
            ],
            "3": [
                1799.79,
                1798.93
            ]
        }
    },
    "vineyard": {
        "Metric": {
            "RAE": [
                1.03,
                0.11
            ],
            "RRSE": [
                1.03,
                0.11
            ]
        },
        "Leaves": [
            1.77,
            0.92
        ],
        "RunTimes": {
            "0": [
                0.06,
                0.05
            ],
            "1": [
                14.12,
                11.8
            ],
            "2": [
                1799.63,
                1799.11
            ],
            "3": [
                1799.46,
                1799.06
            ]
        }
    },
    "boston_corrected": {
        "Metric": {
            "RAE": [
                0.97,
                0.13
            ],
            "RRSE": [
                1.03,
                0.15
            ]
        },
        "Leaves": [
            3.2,
            0.87
        ],
        "RunTimes": {
            "0": [
                0.39,
                0.33
            ],
            "1": [
                1283.7,
                958.97
            ],
            "2": [
                1801.35,
                1800.89
            ],
            "3": [
                1801.46,
                1800.41
            ]
        }
    },
    "forest_fires": {
        "Metric": {
            "RAE": [
                0.7,
                0.04
            ],
            "RRSE": [
                1.04,
                0.02
            ]
        },
        "Leaves": [
            1.37,
            0.6
        ],
        "RunTimes": {
            "0": [
                0.12,
                0.11
            ],
            "1": [
                158.82,
                129.26
            ],
            "2": [
                1799.86,
                1799.28
            ],
            "3": [
                1799.8,
                1798.92
            ]
        }
    },
    "meta": {
        "Metric": {
            "RAE": [
                0.73,
                0.4
            ],
            "RRSE": [
                1.33,
                1.83
            ]
        },
        "Leaves": [
            2.27,
            1.26
        ],
        "RunTimes": {
            "0": [
                0.26,
                0.25
            ],
            "1": [
                150.41,
                64.29
            ],
            "2": [
                1800.54,
                1799.95
            ],
            "3": [
                1800.59,
                1799.75
            ]
        }
    },
    "arsenic-female-lung": {
        "Metric": {
            "RAE": [
                0.74,
                0.55
            ],
            "RRSE": [
                1.19,
                0.86
            ]
        },
        "Leaves": [
            1.63,
            1.08
        ],
        "RunTimes": {
            "0": [
                0.17,
                0.17
            ],
            "1": [
                1276.22,
                1112.26
            ],
            "2": [
                1800.21,
                1799.8
            ],
            "3": [
                1800.22,
                1799.68
            ]
        }
    },
    "arsenic-male-lung": {
        "Metric": {
            "RAE": [
                0.84,
                1.1
            ],
            "RRSE": [
                1.4,
                2.02
            ]
        },
        "Leaves": [
            1.57,
            0.92
        ],
        "RunTimes": {
            "0": [
                0.18,
                0.16
            ],
            "1": [
                1276.62,
                1036.16
            ],
            "2": [
                1824.43,
                1732.05
            ],
            "3": [
                1832.27,
                1710.35
            ]
        }
    },
    "titanic_1": {
        "Metric": {
            "RAE": [
                0.45,
                0.04
            ],
            "RRSE": [
                0.93,
                0.04
            ]
        },
        "Leaves": [
            1.23,
            0.72
        ],
        "RunTimes": {
            "0": [
                0.11,
                0.08
            ],
            "1": [
                26.23,
                20.91
            ],
            "2": [
                1799.58,
                1799.2
            ],
            "3": [
                1799.47,
                1798.87
            ]
        }
    },
    "stock": {
        "Metric": {
            "RAE": [
                0.44,
                0.16
            ],
            "RRSE": [
                0.51,
                0.17
            ]
        },
        "Leaves": [
            3.77,
            0.42
        ],
        "RunTimes": {
            "0": [
                0.18,
                0.1
            ],
            "1": [
                413.91,
                373.59
            ],
            "2": [
                1799.65,
                1798.94
            ],
            "3": [
                1799.48,
                1798.93
            ]
        }
    },
    "Bank-Note": {
        "Metric": {
            "RAE": [
                0.55,
                0.16
            ],
            "RRSE": [
                1.02,
                0.17
            ]
        },
        "Leaves": [
            3.83,
            0.37
        ],
        "RunTimes": {
            "0": [
                0.17,
                0.15
            ],
            "1": [
                624.11,
                484.95
            ],
            "2": [
                1740.2,
                1793.35
            ],
            "3": [
                1740.23,
                1796.94
            ]
        }
    },
    "balloon": {
        "Metric": {
            "RAE": [
                1.51,
                0.24
            ],
            "RRSE": [
                1.34,
                0.27
            ]
        },
        "Leaves": [
            3.7,
            0.9
        ],
        "RunTimes": {
            "0": [
                0.21,
                0.17
            ],
            "1": [
                664.86,
                589.19
            ],
            "2": [
                1799.16,
                1798.41
            ],
            "3": [
                1799.49,
                1798.67
            ]
        }
    },
    "debutanizer": {
        "Metric": {
            "RAE": [
                1.18,
                0.11
            ],
            "RRSE": [
                1.21,
                0.12
            ]
        },
        "Leaves": [
            3.2,
            0.87
        ],
        "RunTimes": {
            "0": [
                0.38,
                0.32
            ],
            "1": [
                1799.16,
                1798.69
            ],
            "2": [
                1799.93,
                1799.35
            ],
            "3": [
                1799.92,
                1799.29
            ]
        }
    },
    "analcatdata_supreme": {
        "Metric": {
            "RAE": [
                0.95,
                0.06
            ],
            "RRSE": [
                1.17,
                0.02
            ]
        },
        "Leaves": [
            1.0,
            0.0
        ],
        "RunTimes": {
            "0": [
                0.44,
                0.37
            ],
            "1": [
                364.71,
                264.02
            ],
            "2": [
                1800.85,
                1799.96
            ],
            "3": [
                1801.01,
                1800.06
            ]
        }
    },
    "Long": {
        "Metric": {
            "RAE": [
                0.23,
                0.03
            ],
            "RRSE": [
                0.68,
                0.04
            ]
        },
        "Leaves": [
            2.5,
            0.85
        ],
        "RunTimes": {
            "0": [
                1.54,
                1.46
            ],
            "1": [
                1800.54,
                1799.54
            ],
            "2": [
                1803.42,
                1802.96
            ],
            "3": [
                1803.47,
                1802.36
            ]
        }
    },
    "KDD": {
        "Metric": {
            "RAE": [
                1.02,
                0.16
            ],
            "RRSE": [
                1.42,
                0.11
            ]
        },
        "Leaves": [
            1.13,
            0.34
        ],
        "RunTimes": {
            "0": [
                4.94,
                4.78
            ],
            "1": [
                896.97,
                1153.18
            ],
            "2": [
                1793.08,
                1593.21
            ],
            "3": [
                1793.17,
                1596.73
            ]
        }
    }
}